datasurveyor/__init__.py
datasurveyor/_binary_features.py
datasurveyor/_categorical_features.py
datasurveyor/_general_features.py
datasurveyor/_unique_features.py
datasurveyor/_utils.py
datasurveyor-0.0.1.dist-info/WHEEL
datasurveyor-0.0.1.dist-info/METADATA
datasurveyor-0.0.1.dist-info/RECORD
