Metadata-Version: 2.1
Name: datasurveyor
Version: 0.0.1
Summary: Data exploration tools.
Home-page: https://github.com/nickbuker/datasurveyor
License: UNKNOWN
Author: Nick Buker
Author-email: nickbuker@gmail.com
Requires-Python: ~=3.6,<4
Classifier: Development Status :: 3 - Alpha
Classifier: License :: OSI Approved :: Apache Software License
Classifier: Programming Language :: Python :: 3
Requires-Dist: pandas >=1.0.4
Requires-Dist: pytest >=5.4.3 ; extra == "test"
Requires-Dist: pytest-cov >=2.10.0 ; extra == "test"
Provides-Extra: test
